dln2_spi_wrapper/__init__.py
dln2_spi_wrapper/dln2_spi_client.py
dln2_spi_wrapper/dln2_spidev.py
dln2_spi_wrapper/py.typed
dln2_spi_wrapper/examples/__init__.py
dln2_spi_wrapper/examples/bpw_tester.py
dln2_spi_wrapper/examples/spidev_test.py
dln2_spi_wrapper-0.1.1.dist-info/licenses/LICENSE
dln2_spi_wrapper-0.1.1.dist-info/METADATA
dln2_spi_wrapper-0.1.1.dist-info/WHEEL
dln2_spi_wrapper-0.1.1.dist-info/entry_points.txt
dln2_spi_wrapper-0.1.1.dist-info/top_level.txt
dln2_spi_wrapper-0.1.1.dist-info/RECORD
