Metadata-Version: 2.4
Name: dln2-spi-wrapper
Version: 0.1.1
Summary: A Python library for DLN2 SPI adapters with spidev-compatible API. Originally developed for Pico USB IO Board.
Author-email: IPM Group <contact@ipmgroup.dev>
Project-URL: Homepage, https://github.com/ipmgroup/dln2_spi_wrapper
Project-URL: Documentation, https://github.com/ipmgroup/dln2_spi_wrapper/blob/master/README.md
Project-URL: Repository, https://github.com/ipmgroup/dln2_spi_wrapper.git
Project-URL: Bug Tracker, https://github.com/ipmgroup/dln2_spi_wrapper/issues
Keywords: dln2,spi,usb,hardware,driver,spidev
Classifier: Development Status :: 4 - Beta
Classifier: Intended Audience :: Developers
Classifier: Topic :: Software Development :: Libraries :: Python Modules
Classifier: Topic :: System :: Hardware :: Hardware Drivers
Classifier: License :: OSI Approved :: Apache Software License
Classifier: Programming Language :: Python :: 3
Classifier: Programming Language :: Python :: 3.7
Classifier: Programming Language :: Python :: 3.8
Classifier: Programming Language :: Python :: 3.9
Classifier: Programming Language :: Python :: 3.10
Classifier: Programming Language :: Python :: 3.11
Classifier: Programming Language :: Python :: 3.12
Classifier: Operating System :: POSIX :: Linux
Classifier: Operating System :: Microsoft :: Windows
Classifier: Operating System :: MacOS
Requires-Python: >=3.7
License-File: LICENSE
Requires-Dist: pyusb>=1.0.0
Provides-Extra: dev
Requires-Dist: pytest>=6.0; extra == "dev"
Requires-Dist: pytest-cov; extra == "dev"
Requires-Dist: black; extra == "dev"
Requires-Dist: flake8; extra == "dev"
Requires-Dist: mypy; extra == "dev"
Requires-Dist: build; extra == "dev"
Requires-Dist: twine; extra == "dev"
Dynamic: license-file
